unidip/__init__.py
unidip/dip.py
unidip/unidip.py
unidip-0.1.1.dist-info/METADATA
unidip-0.1.1.dist-info/RECORD
unidip-0.1.1.dist-info/WHEEL
unidip-0.1.1.dist-info/top_level.txt
