Metadata-Version: 2.1
Name: unidip
Version: 0.1.1
Summary: Python port of the UniDip clustering algorithm
Home-page: http://github.com/BenjaminDoran/unidip
Author: Benjamin Doran
Author-email: benadoran@gmail.com
License: GPL
Platform: UNKNOWN
